nz_bank_validate/__init__.py
nz_bank_validate/__main__.py
nz_bank_validate-1.0.1.dist-info/LICENSE
nz_bank_validate-1.0.1.dist-info/METADATA
nz_bank_validate-1.0.1.dist-info/WHEEL
nz_bank_validate-1.0.1.dist-info/top_level.txt
nz_bank_validate-1.0.1.dist-info/RECORD
