Metadata-Version: 2.1
Name: nz-bank-validate
Version: 1.0.1
Summary: Validates account numbers for New Zealand banks
Home-page: https://github.com/zhaowb/nz-bank-validate.git
Author: Wenbo Zhao
Author-email: zhaowb@gmail.com
License: UNKNOWN
Platform: UNKNOWN
Classifier: Programming Language :: Python :: 3
Classifier: License :: OSI Approved :: MIT License
Classifier: Operating System :: OS Independent
Requires-Python: >=3.6
License-File: LICENSE
